Metadata-Version: 1.0
Name: anon.py
Version: 1.6
Summary: A library for interacting with the API of the Anonym application, because of which the server takes you for a regular user of the application
Home-page: UNKNOWN
Author: UNKNOWN
Author-email: ktoya170214@gmail.com
License: UNKNOWN
Platform: UNKNOWN
